{"derived_from":null,"elements":[{"tags":["clusters","analysis"],"metadata":{},"format2d":{"title_fig":"Cluster Analysis","title_legend":null,"title_ax":"Two Clusters with Centroids","label_x":"X Position","label_y":"Y Position","lim_x_min":0.0,"lim_x_max":6.0,"lim_y_min":0.0,"lim_y_max":6.0},"x":2.9221105500146662,"y":2.884756484355801,"marker":{"color":"blue","size":50.0,"alpha":1.0,"zorder":0.0,"label":"Cluster 1","symbol":"o"},"product_type":"Point2D"},{"tags":["clusters","analysis"],"metadata":{},"format2d":{"title_fig":"Cluster Analysis","title_legend":null,"title_ax":"Two Clusters with Centroids","label_x":"X Position","label_y":"Y Position","lim_x_min":0.0,"lim_x_max":6.0,"lim_y_min":0.0,"lim_y_max":6.0},"x":1.4746245460633847,"y":2.631986255117436,"marker":{"color":"blue","size":50.0,"alpha":1.0,"zorder":0.0,"label":"Cluster 1","symbol":"o"},"product_type":"Point2D"},{"tags":["clusters","analysis"],"metadata":{},"format2d":{"title_fig":"Cluster Analysis","title_legend":null,"title_ax":"Two Clusters with Centroids","label_x":"X Position","label_y":"Y Position","lim_x_min":0.0,"lim_x_max":6.0,"lim_y_min":0.0,"lim_y_max":6.0},"x":1.783588562110246,"y":1.7725727534605404,"marker":{"color":"blue","size":50.0,"alpha":1.0,"zorder":0.0,"label":"Cluster 1","symbol":"o"},"product_type":"Point2D"},{"tags":["clusters","analysis"],"metadata":{},"format2d":{"title_fig":"Cluster Analysis","title_legend":null,"title_ax":"Two Clusters with Centroids","label_x":"X Position","label_y":"Y Position","lim_x_min":0.0,"lim_x_max":6.0,"lim_y_min":0.0,"lim_y_max":6.0},"x":2.0039785262929963,"y":2.962036585363362,"marker":{"color":"blue","size":50.0,"alpha":1.0,"zorder":0.0,"label":"Cluster 1","symbol":"o"},"product_type":"Point2D"},{"tags":["clusters","analysis"],"metadata":{},"format2d":{"title_fig":"Cluster Analysis","title_legend":null,"title_ax":"Two Clusters with Centroids","label_x":"X Position","label_y":"Y Position","lim_x_min":0.0,"lim_x_max":6.0,"lim_y_min":0.0,"lim_y_max":6.0},"x":2.3699683346943203,"y":2.7707833398521133,"marker":{"color":"blue","size":50.0,"alpha":1.0,"zorder":0.0,"label":"Cluster 1","symbol":"o"},"product_type":"Point2D"},{"tags":["clusters","analysis"],"metadata":{},"format2d":{"title_fig":"Cluster Analysis","title_legend":null,"title_ax":"Two Clusters with Centroids","label_x":"X Position","label_y":"Y Position","lim_x_min":0.0,"lim_x_max":6.0,"lim_y_min":0.0,"lim_y_max":6.0},"x":1.927994580165554,"y":1.657316508864739,"marker":{"color":"blue","size":50.0,"alpha":1.0,"zorder":0.0,"label":"Cluster 1","symbol":"o"},"product_type":"Point2D"},{"tags":["clusters","analysis"],"metadata":{},"format2d":{"title_fig":"Cluster Analysis","title_legend":null,"title_ax":"Two Clusters with Centroids","label_x":"X Position","label_y":"Y Position","lim_x_min":0.0,"lim_x_max":6.0,"lim_y_min":0.0,"lim_y_max":6.0},"x":1.8063927536180564,"y":2.101937702751391,"marker":{"color":"blue","size":50.0,"alpha":1.0,"zorder":0.0,"label":"Cluster 1","symbol":"o"},"product_type":"Point2D"},{"tags":["clusters","analysis"],"metadata":{},"format2d":{"title_fig":"Cluster Analysis","title_legend":null,"title_ax":"Two Clusters with Centroids","label_x":"X Position","label_y":"Y Position","lim_x_min":0.0,"lim_x_max":6.0,"lim_y_min":0.0,"lim_y_max":6.0},"x":2.4653415776530445,"y":1.3333361937217414,"marker":{"color":"blue","size":50.0,"alpha":1.0,"zorder":0.0,"label":"Cluster 1","symbol":"o"},"product_type":"Point2D"},{"tags":["clusters","analysis"],"metadata":{},"format2d":{"title_fig":"Cluster Analysis","title_legend":null,"title_ax":"Two Clusters with Centroids","label_x":"X Position","label_y":"Y Position","lim_x_min":0.0,"lim_x_max":6.0,"lim_y_min":0.0,"lim_y_max":6.0},"x":1.586854950972423,"y":2.799459123965884,"marker":{"color":"blue","size":50.0,"alpha":1.0,"zorder":0.0,"label":"Cluster 1","symbol":"o"},"product_type":"Point2D"},{"tags":["clusters","analysis"],"metadata":{},"format2d":{"title_fig":"Cluster Analysis","title_legend":null,"title_ax":"Two Clusters with Centroids","label_x":"X Position","label_y":"Y Position","lim_x_min":0.0,"lim_x_max":6.0,"lim_y_min":0.0,"lim_y_max":6.0},"x":1.8883138200135698,"y":1.754281035173901,"marker":{"color":"blue","size":50.0,"alpha":1.0,"zorder":0.0,"label":"Cluster 1","symbol":"o"},"product_type":"Point2D"},{"tags":["clusters","analysis"],"metadata":{},"format2d":{"title_fig":"Cluster Analysis","title_legend":null,"title_ax":"Two Clusters with Centroids","label_x":"X Position","label_y":"Y Position","lim_x_min":0.0,"lim_x_max":6.0,"lim_y_min":0.0,"lim_y_max":6.0},"x":2.5723931887112936,"y":2.762387415280557,"marker":{"color":"blue","size":50.0,"alpha":1.0,"zorder":0.0,"label":"Cluster 1","symbol":"o"},"product_type":"Point2D"},{"tags":["clusters","analysis"],"metadata":{},"format2d":{"title_fig":"Cluster Analysis","title_legend":null,"title_ax":"Two Clusters with Centroids","label_x":"X Position","label_y":"Y Position","lim_x_min":0.0,"lim_x_max":6.0,"lim_y_min":0.0,"lim_y_max":6.0},"x":2.551683318623435,"y":2.109865725331881,"marker":{"color":"blue","size":50.0,"alpha":1.0,"zorder":0.0,"label":"Cluster 1","symbol":"o"},"product_type":"Point2D"},{"tags":["clusters","analysis"],"metadata":{},"format2d":{"title_fig":"Cluster Analysis","title_legend":null,"title_ax":"Two Clusters with Centroids","label_x":"X Position","label_y":"Y Position","lim_x_min":0.0,"lim_x_max":6.0,"lim_y_min":0.0,"lim_y_max":6.0},"x":1.688586384744068,"y":2.7032878299383976,"marker":{"color":"blue","size":50.0,"alpha":1.0,"zorder":0.0,"label":"Cluster 1","symbol":"o"},"product_type":"Point2D"},{"tags":["clusters","analysis"],"metadata":{},"format2d":{"title_fig":"Cluster Analysis","title_legend":null,"title_ax":"Two Clusters with Centroids","label_x":"X Position","label_y":"Y Position","lim_x_min":0.0,"lim_x_max":6.0,"lim_y_min":0.0,"lim_y_max":6.0},"x":2.335249325098969,"y":2.3485135730474918,"marker":{"color":"blue","size":50.0,"alpha":1.0,"zorder":0.0,"label":"Cluster 1","symbol":"o"},"product_type":"Point2D"},{"tags":["clusters","analysis"],"metadata":{},"format2d":{"title_fig":"Cluster Analysis","title_legend":null,"title_ax":"Two Clusters with Centroids","label_x":"X Position","label_y":"Y Position","lim_x_min":0.0,"lim_x_max":6.0,"lim_y_min":0.0,"lim_y_max":6.0},"x":1.8366863409566716,"y":1.8165841369226898,"marker":{"color":"blue","size":50.0,"alpha":1.0,"zorder":0.0,"label":"Cluster 1","symbol":"o"},"product_type":"Point2D"},{"tags":["clusters","analysis"],"metadata":{},"format2d":{"title_fig":"Cluster Analysis","title_legend":null,"title_ax":"Two Clusters with Centroids","label_x":"X Position","label_y":"Y Position","lim_x_min":0.0,"lim_x_max":6.0,"lim_y_min":0.0,"lim_y_max":6.0},"x":1.595748978291324,"y":1.9236316640142477,"marker":{"color":"blue","size":50.0,"alpha":1.0,"zorder":0.0,"label":"Cluster 1","symbol":"o"},"product_type":"Point2D"},{"tags":["clusters","analysis"],"metadata":{},"format2d":{"title_fig":"Cluster Analysis","title_legend":null,"title_ax":"Two Clusters with Centroids","label_x":"X Position","label_y":"Y Position","lim_x_min":0.0,"lim_x_max":6.0,"lim_y_min":0.0,"lim_y_max":6.0},"x":1.215602394192905,"y":2.700611262945084,"marker":{"color":"blue","size":50.0,"alpha":1.0,"zorder":0.0,"label":"Cluster 1","symbol":"o"},"product_type":"Point2D"},{"tags":["clusters","analysis"],"metadata":{},"format2d":{"title_fig":"Cluster Analysis","title_legend":null,"title_ax":"Two Clusters with Centroids","label_x":"X Position","label_y":"Y Position","lim_x_min":0.0,"lim_x_max":6.0,"lim_y_min":0.0,"lim_y_max":6.0},"x":1.5841498246352896,"y":1.9156963072441944,"marker":{"color":"blue","size":50.0,"alpha":1.0,"zorder":0.0,"label":"Cluster 1","symbol":"o"},"product_type":"Point2D"},{"tags":["clusters","analysis"],"metadata":{},"format2d":{"title_fig":"Cluster Analysis","title_legend":null,"title_ax":"Two Clusters with Centroids","label_x":"X Position","label_y":"Y Position","lim_x_min":0.0,"lim_x_max":6.0,"lim_y_min":0.0,"lim_y_max":6.0},"x":3.1674357594187272,"y":1.4068543868019807,"marker":{"color":"blue","size":50.0,"alpha":1.0,"zorder":0.0,"label":"Cluster 1","symbol":"o"},"product_type":"Point2D"},{"tags":["clusters","analysis"],"metadata":{},"format2d":{"title_fig":"Cluster Analysis","title_legend":null,"title_ax":"Two Clusters with Centroids","label_x":"X Position","label_y":"Y Position","lim_x_min":0.0,"lim_x_max":6.0,"lim_y_min":0.0,"lim_y_max":6.0},"x":2.0439999098209407,"y":2.0678558546699133,"marker":{"color":"blue","size":50.0,"alpha":1.0,"zorder":0.0,"label":"Cluster 1","symbol":"o"},"product_type":"Point2D"},{"tags":["clusters","analysis"],"metadata":{},"format2d":{"title_fig":"Cluster Analysis","title_legend":null,"title_ax":"Two Clusters with Centroids","label_x":"X Position","label_y":"Y Position","lim_x_min":0.0,"lim_x_max":6.0,"lim_y_min":0.0,"lim_y_max":6.0},"x":2.4560099055644913,"y":2.921655468408661,"marker":{"color":"blue","size":50.0,"alpha":1.0,"zorder":0.0,"label":"Cluster 1","symbol":"o"},"product_type":"Point2D"},{"tags":["clusters","analysis"],"metadata":{},"format2d":{"title_fig":"Cluster Analysis","title_legend":null,"title_ax":"Two Clusters with Centroids","label_x":"X Position","label_y":"Y Position","lim_x_min":0.0,"lim_x_max":6.0,"lim_y_min":0.0,"lim_y_max":6.0},"x":2.7678911214118287,"y":1.611739618375668,"marker":{"color":"blue","size":50.0,"alpha":1.0,"zorder":0.0,"label":"Cluster 1","symbol":"o"},"product_type":"Point2D"},{"tags":["clusters","analysis"],"metadata":{},"format2d":{"title_fig":"Cluster Analysis","title_legend":null,"title_ax":"Two Clusters with Centroids","label_x":"X Position","label_y":"Y Position","lim_x_min":0.0,"lim_x_max":6.0,"lim_y_min":0.0,"lim_y_max":6.0},"x":2.080076141453948,"y":0.9917102997106022,"marker":{"color":"blue","size":50.0,"alpha":1.0,"zorder":0.0,"label":"Cluster 1","symbol":"o"},"product_type":"Point2D"},{"tags":["clusters","analysis"],"metadata":{},"format2d":{"title_fig":"Cluster Analysis","title_legend":null,"title_ax":"Two Clusters with Centroids","label_x":"X Position","label_y":"Y Position","lim_x_min":0.0,"lim_x_max":6.0,"lim_y_min":0.0,"lim_y_max":6.0},"x":2.4843018842639286,"y":2.192463072716355,"marker":{"color":"blue","size":50.0,"alpha":1.0,"zorder":0.0,"label":"Cluster 1","symbol":"o"},"product_type":"Point2D"},{"tags":["clusters","analysis"],"metadata":{},"format2d":{"title_fig":"Cluster Analysis","title_legend":null,"title_ax":"Two Clusters with Centroids","label_x":"X Position","label_y":"Y Position","lim_x_min":0.0,"lim_x_max":6.0,"lim_y_min":0.0,"lim_y_max":6.0},"x":2.465222799152521,"y":2.5962657219950787,"marker":{"color":"blue","size":50.0,"alpha":1.0,"zorder":0.0,"label":"Cluster 1","symbol":"o"},"product_type":"Point2D"},{"tags":["clusters","analysis"],"metadata":{},"format2d":{"title_fig":"Cluster Analysis","title_legend":null,"title_ax":"Two Clusters with Centroids","label_x":"X Position","label_y":"Y Position","lim_x_min":0.0,"lim_x_max":6.0,"lim_y_min":0.0,"lim_y_max":6.0},"x":1.5310468651343898,"y":2.175064878871786,"marker":{"color":"blue","size":50.0,"alpha":1.0,"zorder":0.0,"label":"Cluster 1","symbol":"o"},"product_type":"Point2D"},{"tags":["clusters","analysis"],"metadata":{},"format2d":{"title_fig":"Cluster Analysis","title_legend":null,"title_ax":"Two Clusters with Centroids","label_x":"X Position","label_y":"Y Position","lim_x_min":0.0,"lim_x_max":6.0,"lim_y_min":0.0,"lim_y_max":6.0},"x":1.943089297749337,"y":2.1812480513055883,"marker":{"color":"blue","size":50.0,"alpha":1.0,"zorder":0.0,"label":"Cluster 1","symbol":"o"},"product_type":"Point2D"},{"tags":["clusters","analysis"],"metadata":{},"format2d":{"title_fig":"Cluster Analysis","title_legend":null,"title_ax":"Two Clusters with Centroids","label_x":"X Position","label_y":"Y Position","lim_x_min":0.0,"lim_x_max":6.0,"lim_y_min":0.0,"lim_y_max":6.0},"x":2.0596742226397073,"y":1.8257918057687221,"marker":{"color":"blue","size":50.0,"alpha":1.0,"zorder":0.0,"label":"Cluster 1","symbol":"o"},"product_type":"Point2D"},{"tags":["clusters","analysis"],"metadata":{},"format2d":{"title_fig":"Cluster Analysis","title_legend":null,"title_ax":"Two Clusters with Centroids","label_x":"X Position","label_y":"Y Position","lim_x_min":0.0,"lim_x_max":6.0,"lim_y_min":0.0,"lim_y_max":6.0},"x":2.114250625686339,"y":1.5869882320185276,"marker":{"color":"blue","size":50.0,"alpha":1.0,"zorder":0.0,"label":"Cluster 1","symbol":"o"},"product_type":"Point2D"},{"tags":["clusters","analysis"],"metadata":{},"format2d":{"title_fig":"Cluster Analysis","title_legend":null,"title_ax":"Two Clusters with Centroids","label_x":"X Position","label_y":"Y Position","lim_x_min":0.0,"lim_x_max":6.0,"lim_y_min":0.0,"lim_y_max":6.0},"x":1.11126258528492,"y":1.6232254475196248,"marker":{"color":"blue","size":50.0,"alpha":1.0,"zorder":0.0,"label":"Cluster 1","symbol":"o"},"product_type":"Point2D"},{"tags":["clusters","analysis"],"metadata":{},"format2d":{"title_fig":"Cluster Analysis","title_legend":null,"title_ax":"Two Clusters with Centroids","label_x":"X Position","label_y":"Y Position","lim_x_min":0.0,"lim_x_max":6.0,"lim_y_min":0.0,"lim_y_max":6.0},"x":1.8348905632217076,"y":1.8746052337496495,"marker":{"color":"blue","size":50.0,"alpha":1.0,"zorder":0.0,"label":"Cluster 1","symbol":"o"},"product_type":"Point2D"},{"tags":["clusters","analysis"],"metadata":{},"format2d":{"title_fig":"Cluster Analysis","title_legend":null,"title_ax":"Two Clusters with Centroids","label_x":"X Position","label_y":"Y Position","lim_x_min":0.0,"lim_x_max":6.0,"lim_y_min":0.0,"lim_y_max":6.0},"x":1.3643889838239016,"y":1.6746700318901517,"marker":{"color":"blue","size":50.0,"alpha":1.0,"zorder":0.0,"label":"Cluster 1","symbol":"o"},"product_type":"Point2D"},{"tags":["clusters","analysis"],"metadata":{},"format2d":{"title_fig":"Cluster Analysis","title_legend":null,"title_ax":"Two Clusters with Centroids","label_x":"X Position","label_y":"Y Position","lim_x_min":0.0,"lim_x_max":6.0,"lim_y_min":0.0,"lim_y_max":6.0},"x":2.466418754928247,"y":1.1932299240480968,"marker":{"color":"blue","size":50.0,"alpha":1.0,"zorder":0.0,"label":"Cluster 1","symbol":"o"},"product_type":"Point2D"},{"tags":["clusters","analysis"],"metadata":{},"format2d":{"title_fig":"Cluster Analysis","title_legend":null,"title_ax":"Two Clusters with Centroids","label_x":"X Position","label_y":"Y Position","lim_x_min":0.0,"lim_x_max":6.0,"lim_y_min":0.0,"lim_y_max":6.0},"x":1.9246665171247088,"y":1.1374941464786734,"marker":{"color":"blue","size":50.0,"alpha":1.0,"zorder":0.0,"label":"Cluster 1","symbol":"o"},"product_type":"Point2D"},{"tags":["clusters","analysis"],"metadata":{},"format2d":{"title_fig":"Cluster Analysis","title_legend":null,"title_ax":"Two Clusters with Centroids","label_x":"X Position","label_y":"Y Position","lim_x_min":0.0,"lim_x_max":6.0,"lim_y_min":0.0,"lim_y_max":6.0},"x":2.1676429529213523,"y":2.3874562395479533,"marker":{"color":"blue","size":50.0,"alpha":1.0,"zorder":0.0,"label":"Cluster 1","symbol":"o"},"product_type":"Point2D"},{"tags":["clusters","analysis"],"metadata":{},"format2d":{"title_fig":"Cluster Analysis","title_legend":null,"title_ax":"Two Clusters with Centroids","label_x":"X Position","label_y":"Y Position","lim_x_min":0.0,"lim_x_max":6.0,"lim_y_min":0.0,"lim_y_max":6.0},"x":1.0395313745462589,"y":2.2416977843735584,"marker":{"color":"blue","size":50.0,"alpha":1.0,"zorder":0.0,"label":"Cluster 1","symbol":"o"},"product_type":"Point2D"},{"tags":["clusters","analysis"],"metadata":{},"format2d":{"title_fig":"Cluster Analysis","title_legend":null,"title_ax":"Two Clusters with Centroids","label_x":"X Position","label_y":"Y Position","lim_x_min":0.0,"lim_x_max":6.0,"lim_y_min":0.0,"lim_y_max":6.0},"x":1.906230284264933,"y":1.4553576284841574,"marker":{"color":"blue","size":50.0,"alpha":1.0,"zorder":0.0,"label":"Cluster 1","symbol":"o"},"product_type":"Point2D"},{"tags":["clusters","analysis"],"metadata":{},"format2d":{"title_fig":"Cluster Analysis","title_legend":null,"title_ax":"Two Clusters with Centroids","label_x":"X Position","label_y":"Y Position","lim_x_min":0.0,"lim_x_max":6.0,"lim_y_min":0.0,"lim_y_max":6.0},"x":2.1794096481709486,"y":2.008017581610824,"marker":{"color":"blue","size":50.0,"alpha":1.0,"zorder":0.0,"label":"Cluster 1","symbol":"o"},"product_type":"Point2D"},{"tags":["clusters","analysis"],"metadata":{},"format2d":{"title_fig":"Cluster Analysis","title_legend":null,"title_ax":"Two Clusters with Centroids","label_x":"X Position","label_y":"Y Position","lim_x_min":0.0,"lim_x_max":6.0,"lim_y_min":0.0,"lim_y_max":6.0},"x":2.1835238895549542,"y":2.4735388349263276,"marker":{"color":"blue","size":50.0,"alpha":1.0,"zorder":0.0,"label":"Cluster 1","symbol":"o"},"product_type":"Point2D"},{"tags":["clusters","analysis"],"metadata":{},"format2d":{"title_fig":"Cluster Analysis","title_legend":null,"title_ax":"Two Clusters with Centroids","label_x":"X Position","label_y":"Y Position","lim_x_min":0.0,"lim_x_max":6.0,"lim_y_min":0.0,"lim_y_max":6.0},"x":2.4575438269548857,"y":1.6821474370792102,"marker":{"color":"blue","size":50.0,"alpha":1.0,"zorder":0.0,"label":"Cluster 1","symbol":"o"},"product_type":"Point2D"},{"tags":["clusters","analysis"],"metadata":{},"format2d":{"title_fig":"Cluster Analysis","title_legend":null,"title_ax":"Two Clusters with Centroids","label_x":"X Position","label_y":"Y Position","lim_x_min":0.0,"lim_x_max":6.0,"lim_y_min":0.0,"lim_y_max":6.0},"x":1.8009176804984142,"y":1.4291425974218304,"marker":{"color":"blue","size":50.0,"alpha":1.0,"zorder":0.0,"label":"Cluster 1","symbol":"o"},"product_type":"Point2D"},{"tags":["clusters","analysis"],"metadata":{},"format2d":{"title_fig":"Cluster Analysis","title_legend":null,"title_ax":"Two Clusters with Centroids","label_x":"X Position","label_y":"Y Position","lim_x_min":0.0,"lim_x_max":6.0,"lim_y_min":0.0,"lim_y_max":6.0},"x":1.8240446284788785,"y":1.4933509738999016,"marker":{"color":"blue","size":50.0,"alpha":1.0,"zorder":0.0,"label":"Cluster 1","symbol":"o"},"product_type":"Point2D"},{"tags":["clusters","analysis"],"metadata":{},"format2d":{"title_fig":"Cluster Analysis","title_legend":null,"title_ax":"Two Clusters with Centroids","label_x":"X Position","label_y":"Y Position","lim_x_min":0.0,"lim_x_max":6.0,"lim_y_min":0.0,"lim_y_max":6.0},"x":1.7431824283168278,"y":1.3794634083872546,"marker":{"color":"blue","size":50.0,"alpha":1.0,"zorder":0.0,"label":"Cluster 1","symbol":"o"},"product_type":"Point2D"},{"tags":["clusters","analysis"],"metadata":{},"format2d":{"title_fig":"Cluster Analysis","title_legend":null,"title_ax":"Two Clusters with Centroids","label_x":"X Position","label_y":"Y Position","lim_x_min":0.0,"lim_x_max":6.0,"lim_y_min":0.0,"lim_y_max":6.0},"x":2.408714442691814,"y":1.7246580742003341,"marker":{"color":"blue","size":50.0,"alpha":1.0,"zorder":0.0,"label":"Cluster 1","symbol":"o"},"product_type":"Point2D"},{"tags":["clusters","analysis"],"metadata":{},"format2d":{"title_fig":"Cluster Analysis","title_legend":null,"title_ax":"Two Clusters with Centroids","label_x":"X Position","label_y":"Y Position","lim_x_min":0.0,"lim_x_max":6.0,"lim_y_min":0.0,"lim_y_max":6.0},"x":1.5443566317769706,"y":1.662175799816247,"marker":{"color":"blue","size":50.0,"alpha":1.0,"zorder":0.0,"label":"Cluster 1","symbol":"o"},"product_type":"Point2D"},{"tags":["clusters","analysis"],"metadata":{},"format2d":{"title_fig":"Cluster Analysis","title_legend":null,"title_ax":"Two Clusters with Centroids","label_x":"X Position","label_y":"Y Position","lim_x_min":0.0,"lim_x_max":6.0,"lim_y_min":0.0,"lim_y_max":6.0},"x":2.22343174819289,"y":1.0920344171276626,"marker":{"color":"blue","size":50.0,"alpha":1.0,"zorder":0.0,"label":"Cluster 1","symbol":"o"},"product_type":"Point2D"},{"tags":["clusters","analysis"],"metadata":{},"format2d":{"title_fig":"Cluster Analysis","title_legend":null,"title_ax":"Two Clusters with Centroids","label_x":"X Position","label_y":"Y Position","lim_x_min":0.0,"lim_x_max":6.0,"lim_y_min":0.0,"lim_y_max":6.0},"x":2.390458652737501,"y":1.5706107670736045,"marker":{"color":"blue","size":50.0,"alpha":1.0,"zorder":0.0,"label":"Cluster 1","symbol":"o"},"product_type":"Point2D"},{"tags":["clusters","analysis"],"metadata":{},"format2d":{"title_fig":"Cluster Analysis","title_legend":null,"title_ax":"Two Clusters with Centroids","label_x":"X Position","label_y":"Y Position","lim_x_min":0.0,"lim_x_max":6.0,"lim_y_min":0.0,"lim_y_max":6.0},"x":1.3309546421179639,"y":2.1294315792816447,"marker":{"color":"blue","size":50.0,"alpha":1.0,"zorder":0.0,"label":"Cluster 1","symbol":"o"},"product_type":"Point2D"},{"tags":["clusters","analysis"],"metadata":{},"format2d":{"title_fig":"Cluster Analysis","title_legend":null,"title_ax":"Two Clusters with Centroids","label_x":"X Position","label_y":"Y Position","lim_x_min":0.0,"lim_x_max":6.0,"lim_y_min":0.0,"lim_y_max":6.0},"x":2.6626031689429936,"y":3.1350169295241352,"marker":{"color":"blue","size":50.0,"alpha":1.0,"zorder":0.0,"label":"Cluster 1","symbol":"o"},"product_type":"Point2D"},{"tags":["clusters","analysis"],"metadata":{},"format2d":{"title_fig":"Cluster Analysis","title_legend":null,"title_ax":"Two Clusters with Centroids","label_x":"X Position","label_y":"Y Position","lim_x_min":0.0,"lim_x_max":6.0,"lim_y_min":0.0,"lim_y_max":6.0},"x":2.23554954935192,"y":2.4069056133265705,"marker":{"color":"blue","size":50.0,"alpha":1.0,"zorder":0.0,"label":"Cluster 1","symbol":"o"},"product_type":"Point2D"},{"tags":["clusters","analysis"],"metadata":{},"format2d":{"title_fig":"Cluster Analysis","title_legend":null,"title_ax":"Two Clusters with Centroids","label_x":"X Position","label_y":"Y Position","lim_x_min":0.0,"lim_x_max":6.0,"lim_y_min":0.0,"lim_y_max":6.0},"x":3.382758202303417,"y":2.8357669954638136,"marker":{"color":"red","size":50.0,"alpha":1.0,"zorder":0.0,"label":"Cluster 2","symbol":"o"},"product_type":"Point2D"},{"tags":["clusters","analysis"],"metadata":{},"format2d":{"title_fig":"Cluster Analysis","title_legend":null,"title_ax":"Two Clusters with Centroids","label_x":"X Position","label_y":"Y Position","lim_x_min":0.0,"lim_x_max":6.0,"lim_y_min":0.0,"lim_y_max":6.0},"x":4.428274306474105,"y":4.471558988362641,"marker":{"color":"red","size":50.0,"alpha":1.0,"zorder":0.0,"label":"Cluster 2","symbol":"o"},"product_type":"Point2D"},{"tags":["clusters","analysis"],"metadata":{},"format2d":{"title_fig":"Cluster Analysis","title_legend":null,"title_ax":"Two Clusters with Centroids","label_x":"X Position","label_y":"Y Position","lim_x_min":0.0,"lim_x_max":6.0,"lim_y_min":0.0,"lim_y_max":6.0},"x":3.62965793140442,"y":4.458578954658716,"marker":{"color":"red","size":50.0,"alpha":1.0,"zorder":0.0,"label":"Cluster 2","symbol":"o"},"product_type":"Point2D"},{"tags":["clusters","analysis"],"metadata":{},"format2d":{"title_fig":"Cluster Analysis","title_legend":null,"title_ax":"Two Clusters with Centroids","label_x":"X Position","label_y":"Y Position","lim_x_min":0.0,"lim_x_max":6.0,"lim_y_min":0.0,"lim_y_max":6.0},"x":3.9102558172377573,"y":3.811591731725235,"marker":{"color":"red","size":50.0,"alpha":1.0,"zorder":0.0,"label":"Cluster 2","symbol":"o"},"product_type":"Point2D"},{"tags":["clusters","analysis"],"metadata":{},"format2d":{"title_fig":"Cluster Analysis","title_legend":null,"title_ax":"Two Clusters with Centroids","label_x":"X Position","label_y":"Y Position","lim_x_min":0.0,"lim_x_max":6.0,"lim_y_min":0.0,"lim_y_max":6.0},"x":4.936495930390198,"y":4.402746044884202,"marker":{"color":"red","size":50.0,"alpha":1.0,"zorder":0.0,"label":"Cluster 2","symbol":"o"},"product_type":"Point2D"},{"tags":["clusters","analysis"],"metadata":{},"format2d":{"title_fig":"Cluster Analysis","title_legend":null,"title_ax":"Two Clusters with Centroids","label_x":"X Position","label_y":"Y Position","lim_x_min":0.0,"lim_x_max":6.0,"lim_y_min":0.0,"lim_y_max":6.0},"x":4.468845452303013,"y":4.406780827194744,"marker":{"color":"red","size":50.0,"alpha":1.0,"zorder":0.0,"label":"Cluster 2","symbol":"o"},"product_type":"Point2D"},{"tags":["clusters","analysis"],"metadata":{},"format2d":{"title_fig":"Cluster Analysis","title_legend":null,"title_ax":"Two Clusters with Centroids","label_x":"X Position","label_y":"Y Position","lim_x_min":0.0,"lim_x_max":6.0,"lim_y_min":0.0,"lim_y_max":6.0},"x":4.633960710634268,"y":4.415460252711927,"marker":{"color":"red","size":50.0,"alpha":1.0,"zorder":0.0,"label":"Cluster 2","symbol":"o"},"product_type":"Point2D"},{"tags":["clusters","analysis"],"metadata":{},"format2d":{"title_fig":"Cluster Analysis","title_legend":null,"title_ax":"Two Clusters with Centroids","label_x":"X Position","label_y":"Y Position","lim_x_min":0.0,"lim_x_max":6.0,"lim_y_min":0.0,"lim_y_max":6.0},"x":3.767322590132426,"y":4.174651666497631,"marker":{"color":"red","size":50.0,"alpha":1.0,"zorder":0.0,"label":"Cluster 2","symbol":"o"},"product_type":"Point2D"},{"tags":["clusters","analysis"],"metadata":{},"format2d":{"title_fig":"Cluster Analysis","title_legend":null,"title_ax":"Two Clusters with Centroids","label_x":"X Position","label_y":"Y Position","lim_x_min":0.0,"lim_x_max":6.0,"lim_y_min":0.0,"lim_y_max":6.0},"x":3.4475993087600525,"y":3.6471919721288493,"marker":{"color":"red","size":50.0,"alpha":1.0,"zorder":0.0,"label":"Cluster 2","symbol":"o"},"product_type":"Point2D"},{"tags":["clusters","analysis"],"metadata":{},"format2d":{"title_fig":"Cluster Analysis","title_legend":null,"title_ax":"Two Clusters with Centroids","label_x":"X Position","label_y":"Y Position","lim_x_min":0.0,"lim_x_max":6.0,"lim_y_min":0.0,"lim_y_max":6.0},"x":4.470885402673881,"y":4.096965508518036,"marker":{"color":"red","size":50.0,"alpha":1.0,"zorder":0.0,"label":"Cluster 2","symbol":"o"},"product_type":"Point2D"},{"tags":["clusters","analysis"],"metadata":{},"format2d":{"title_fig":"Cluster Analysis","title_legend":null,"title_ax":"Two Clusters with Centroids","label_x":"X Position","label_y":"Y Position","lim_x_min":0.0,"lim_x_max":6.0,"lim_y_min":0.0,"lim_y_max":6.0},"x":3.7540586570592165,"y":3.8913496649698387,"marker":{"color":"red","size":50.0,"alpha":1.0,"zorder":0.0,"label":"Cluster 2","symbol":"o"},"product_type":"Point2D"},{"tags":["clusters","analysis"],"metadata":{},"format2d":{"title_fig":"Cluster Analysis","title_legend":null,"title_ax":"Two Clusters with Centroids","label_x":"X Position","label_y":"Y Position","lim_x_min":0.0,"lim_x_max":6.0,"lim_y_min":0.0,"lim_y_max":6.0},"x":3.7139556519680474,"y":3.775787375751351,"marker":{"color":"red","size":50.0,"alpha":1.0,"zorder":0.0,"label":"Cluster 2","symbol":"o"},"product_type":"Point2D"},{"tags":["clusters","analysis"],"metadata":{},"format2d":{"title_fig":"Cluster Analysis","title_legend":null,"title_ax":"Two Clusters with Centroids","label_x":"X Position","label_y":"Y Position","lim_x_min":0.0,"lim_x_max":6.0,"lim_y_min":0.0,"lim_y_max":6.0},"x":3.763591507467401,"y":2.994756447516303,"marker":{"color":"red","size":50.0,"alpha":1.0,"zorder":0.0,"label":"Cluster 2","symbol":"o"},"product_type":"Point2D"},{"tags":["clusters","analysis"],"metadata":{},"format2d":{"title_fig":"Cluster Analysis","title_legend":null,"title_ax":"Two Clusters with Centroids","label_x":"X Position","label_y":"Y Position","lim_x_min":0.0,"lim_x_max":6.0,"lim_y_min":0.0,"lim_y_max":6.0},"x":4.066671098074033,"y":4.431265525779744,"marker":{"color":"red","size":50.0,"alpha":1.0,"zorder":0.0,"label":"Cluster 2","symbol":"o"},"product_type":"Point2D"},{"tags":["clusters","analysis"],"metadata":{},"format2d":{"title_fig":"Cluster Analysis","title_legend":null,"title_ax":"Two Clusters with Centroids","label_x":"X Position","label_y":"Y Position","lim_x_min":0.0,"lim_x_max":6.0,"lim_y_min":0.0,"lim_y_max":6.0},"x":3.660029968927538,"y":4.509520314123512,"marker":{"color":"red","size":50.0,"alpha":1.0,"zorder":0.0,"label":"Cluster 2","symbol":"o"},"product_type":"Point2D"},{"tags":["clusters","analysis"],"metadata":{},"format2d":{"title_fig":"Cluster Analysis","title_legend":null,"title_ax":"Two Clusters with Centroids","label_x":"X Position","label_y":"Y Position","lim_x_min":0.0,"lim_x_max":6.0,"lim_y_min":0.0,"lim_y_max":6.0},"x":4.159549112221466,"y":4.290622958059059,"marker":{"color":"red","size":50.0,"alpha":1.0,"zorder":0.0,"label":"Cluster 2","symbol":"o"},"product_type":"Point2D"},{"tags":["clusters","analysis"],"metadata":{},"format2d":{"title_fig":"Cluster Analysis","title_legend":null,"title_ax":"Two Clusters with Centroids","label_x":"X Position","label_y":"Y Position","lim_x_min":0.0,"lim_x_max":6.0,"lim_y_min":0.0,"lim_y_max":6.0},"x":3.9872040749763826,"y":2.9261918541399576,"marker":{"color":"red","size":50.0,"alpha":1.0,"zorder":0.0,"label":"Cluster 2","symbol":"o"},"product_type":"Point2D"},{"tags":["clusters","analysis"],"metadata":{},"format2d":{"title_fig":"Cluster Analysis","title_legend":null,"title_ax":"Two Clusters with Centroids","label_x":"X Position","label_y":"Y Position","lim_x_min":0.0,"lim_x_max":6.0,"lim_y_min":0.0,"lim_y_max":6.0},"x":3.2024204607156226,"y":4.078751680132195,"marker":{"color":"red","size":50.0,"alpha":1.0,"zorder":0.0,"label":"Cluster 2","symbol":"o"},"product_type":"Point2D"},{"tags":["clusters","analysis"],"metadata":{},"format2d":{"title_fig":"Cluster Analysis","title_legend":null,"title_ax":"Two Clusters with Centroids","label_x":"X Position","label_y":"Y Position","lim_x_min":0.0,"lim_x_max":6.0,"lim_y_min":0.0,"lim_y_max":6.0},"x":4.538091411657851,"y":3.643539331848956,"marker":{"color":"red","size":50.0,"alpha":1.0,"zorder":0.0,"label":"Cluster 2","symbol":"o"},"product_type":"Point2D"},{"tags":["clusters","analysis"],"metadata":{},"format2d":{"title_fig":"Cluster Analysis","title_legend":null,"title_ax":"Two Clusters with Centroids","label_x":"X Position","label_y":"Y Position","lim_x_min":0.0,"lim_x_max":6.0,"lim_y_min":0.0,"lim_y_max":6.0},"x":3.965035287321225,"y":4.432598707757688,"marker":{"color":"red","size":50.0,"alpha":1.0,"zorder":0.0,"label":"Cluster 2","symbol":"o"},"product_type":"Point2D"},{"tags":["clusters","analysis"],"metadata":{},"format2d":{"title_fig":"Cluster Analysis","title_legend":null,"title_ax":"Two Clusters with Centroids","label_x":"X Position","label_y":"Y Position","lim_x_min":0.0,"lim_x_max":6.0,"lim_y_min":0.0,"lim_y_max":6.0},"x":3.6621080146827634,"y":3.652287053701343,"marker":{"color":"red","size":50.0,"alpha":1.0,"zorder":0.0,"label":"Cluster 2","symbol":"o"},"product_type":"Point2D"},{"tags":["clusters","analysis"],"metadata":{},"format2d":{"title_fig":"Cluster Analysis","title_legend":null,"title_ax":"Two Clusters with Centroids","label_x":"X Position","label_y":"Y Position","lim_x_min":0.0,"lim_x_max":6.0,"lim_y_min":0.0,"lim_y_max":6.0},"x":3.901121357510579,"y":4.1436864483174025,"marker":{"color":"red","size":50.0,"alpha":1.0,"zorder":0.0,"label":"Cluster 2","symbol":"o"},"product_type":"Point2D"},{"tags":["clusters","analysis"],"metadata":{},"format2d":{"title_fig":"Cluster Analysis","title_legend":null,"title_ax":"Two Clusters with Centroids","label_x":"X Position","label_y":"Y Position","lim_x_min":0.0,"lim_x_max":6.0,"lim_y_min":0.0,"lim_y_max":6.0},"x":4.2714020384639815,"y":4.543184058881175,"marker":{"color":"red","size":50.0,"alpha":1.0,"zorder":0.0,"label":"Cluster 2","symbol":"o"},"product_type":"Point2D"},{"tags":["clusters","analysis"],"metadata":{},"format2d":{"title_fig":"Cluster Analysis","title_legend":null,"title_ax":"Two Clusters with Centroids","label_x":"X Position","label_y":"Y Position","lim_x_min":0.0,"lim_x_max":6.0,"lim_y_min":0.0,"lim_y_max":6.0},"x":3.7446734211539194,"y":4.005848014244756,"marker":{"color":"red","size":50.0,"alpha":1.0,"zorder":0.0,"label":"Cluster 2","symbol":"o"},"product_type":"Point2D"},{"tags":["clusters","analysis"],"metadata":{},"format2d":{"title_fig":"Cluster Analysis","title_legend":null,"title_ax":"Two Clusters with Centroids","label_x":"X Position","label_y":"Y Position","lim_x_min":0.0,"lim_x_max":6.0,"lim_y_min":0.0,"lim_y_max":6.0},"x":4.437678788457105,"y":4.3059969536388065,"marker":{"color":"red","size":50.0,"alpha":1.0,"zorder":0.0,"label":"Cluster 2","symbol":"o"},"product_type":"Point2D"},{"tags":["clusters","analysis"],"metadata":{},"format2d":{"title_fig":"Cluster Analysis","title_legend":null,"title_ax":"Two Clusters with Centroids","label_x":"X Position","label_y":"Y Position","lim_x_min":0.0,"lim_x_max":6.0,"lim_y_min":0.0,"lim_y_max":6.0},"x":4.7082499123918495,"y":3.6739416163489365,"marker":{"color":"red","size":50.0,"alpha":1.0,"zorder":0.0,"label":"Cluster 2","symbol":"o"},"product_type":"Point2D"},{"tags":["clusters","analysis"],"metadata":{},"format2d":{"title_fig":"Cluster Analysis","title_legend":null,"title_ax":"Two Clusters with Centroids","label_x":"X Position","label_y":"Y Position","lim_x_min":0.0,"lim_x_max":6.0,"lim_y_min":0.0,"lim_y_max":6.0},"x":3.1636530136413596,"y":5.126730408763378,"marker":{"color":"red","size":50.0,"alpha":1.0,"zorder":0.0,"label":"Cluster 2","symbol":"o"},"product_type":"Point2D"},{"tags":["clusters","analysis"],"metadata":{},"format2d":{"title_fig":"Cluster Analysis","title_legend":null,"title_ax":"Two Clusters with Centroids","label_x":"X Position","label_y":"Y Position","lim_x_min":0.0,"lim_x_max":6.0,"lim_y_min":0.0,"lim_y_max":6.0},"x":3.5976473073605817,"y":4.867620531273806,"marker":{"color":"red","size":50.0,"alpha":1.0,"zorder":0.0,"label":"Cluster 2","symbol":"o"},"product_type":"Point2D"},{"tags":["clusters","analysis"],"metadata":{},"format2d":{"title_fig":"Cluster Analysis","title_legend":null,"title_ax":"Two Clusters with Centroids","label_x":"X Position","label_y":"Y Position","lim_x_min":0.0,"lim_x_max":6.0,"lim_y_min":0.0,"lim_y_max":6.0},"x":4.20833087151454,"y":4.664878193848876,"marker":{"color":"red","size":50.0,"alpha":1.0,"zorder":0.0,"label":"Cluster 2","symbol":"o"},"product_type":"Point2D"},{"tags":["clusters","analysis"],"metadata":{},"format2d":{"title_fig":"Cluster Analysis","title_legend":null,"title_ax":"Two Clusters with Centroids","label_x":"X Position","label_y":"Y Position","lim_x_min":0.0,"lim_x_max":6.0,"lim_y_min":0.0,"lim_y_max":6.0},"x":3.1878901734227094,"y":4.4567407611391054,"marker":{"color":"red","size":50.0,"alpha":1.0,"zorder":0.0,"label":"Cluster 2","symbol":"o"},"product_type":"Point2D"},{"tags":["clusters","analysis"],"metadata":{},"format2d":{"title_fig":"Cluster Analysis","title_legend":null,"title_ax":"Two Clusters with Centroids","label_x":"X Position","label_y":"Y Position","lim_x_min":0.0,"lim_x_max":6.0,"lim_y_min":0.0,"lim_y_max":6.0},"x":3.8086379891204536,"y":4.072943814123825,"marker":{"color":"red","size":50.0,"alpha":1.0,"zorder":0.0,"label":"Cluster 2","symbol":"o"},"product_type":"Point2D"},{"tags":["clusters","analysis"],"metadata":{},"format2d":{"title_fig":"Cluster Analysis","title_legend":null,"title_ax":"Two Clusters with Centroids","label_x":"X Position","label_y":"Y Position","lim_x_min":0.0,"lim_x_max":6.0,"lim_y_min":0.0,"lim_y_max":6.0},"x":3.7910685636061574,"y":4.400951559504923,"marker":{"color":"red","size":50.0,"alpha":1.0,"zorder":0.0,"label":"Cluster 2","symbol":"o"},"product_type":"Point2D"},{"tags":["clusters","analysis"],"metadata":{},"format2d":{"title_fig":"Cluster Analysis","title_legend":null,"title_ax":"Two Clusters with Centroids","label_x":"X Position","label_y":"Y Position","lim_x_min":0.0,"lim_x_max":6.0,"lim_y_min":0.0,"lim_y_max":6.0},"x":4.27678923562839,"y":4.823339286279603,"marker":{"color":"red","size":50.0,"alpha":1.0,"zorder":0.0,"label":"Cluster 2","symbol":"o"},"product_type":"Point2D"},{"tags":["clusters","analysis"],"metadata":{},"format2d":{"title_fig":"Cluster Analysis","title_legend":null,"title_ax":"Two Clusters with Centroids","label_x":"X Position","label_y":"Y Position","lim_x_min":0.0,"lim_x_max":6.0,"lim_y_min":0.0,"lim_y_max":6.0},"x":4.351544270970793,"y":4.093170666710282,"marker":{"color":"red","size":50.0,"alpha":1.0,"zorder":0.0,"label":"Cluster 2","symbol":"o"},"product_type":"Point2D"},{"tags":["clusters","analysis"],"metadata":{},"format2d":{"title_fig":"Cluster Analysis","title_legend":null,"title_ax":"Two Clusters with Centroids","label_x":"X Position","label_y":"Y Position","lim_x_min":0.0,"lim_x_max":6.0,"lim_y_min":0.0,"lim_y_max":6.0},"x":4.59161407824672,"y":3.8055275539374853,"marker":{"color":"red","size":50.0,"alpha":1.0,"zorder":0.0,"label":"Cluster 2","symbol":"o"},"product_type":"Point2D"},{"tags":["clusters","analysis"],"metadata":{},"format2d":{"title_fig":"Cluster Analysis","title_legend":null,"title_ax":"Two Clusters with Centroids","label_x":"X Position","label_y":"Y Position","lim_x_min":0.0,"lim_x_max":6.0,"lim_y_min":0.0,"lim_y_max":6.0},"x":3.35229933525572,"y":3.9396088933717732,"marker":{"color":"red","size":50.0,"alpha":1.0,"zorder":0.0,"label":"Cluster 2","symbol":"o"},"product_type":"Point2D"},{"tags":["clusters","analysis"],"metadata":{},"format2d":{"title_fig":"Cluster Analysis","title_legend":null,"title_ax":"Two Clusters with Centroids","label_x":"X Position","label_y":"Y Position","lim_x_min":0.0,"lim_x_max":6.0,"lim_y_min":0.0,"lim_y_max":6.0},"x":3.8722273102673106,"y":3.928011387242411,"marker":{"color":"red","size":50.0,"alpha":1.0,"zorder":0.0,"label":"Cluster 2","symbol":"o"},"product_type":"Point2D"},{"tags":["clusters","analysis"],"metadata":{},"format2d":{"title_fig":"Cluster Analysis","title_legend":null,"title_ax":"Two Clusters with Centroids","label_x":"X Position","label_y":"Y Position","lim_x_min":0.0,"lim_x_max":6.0,"lim_y_min":0.0,"lim_y_max":6.0},"x":3.6384737109644765,"y":3.9224075309983593,"marker":{"color":"red","size":50.0,"alpha":1.0,"zorder":0.0,"label":"Cluster 2","symbol":"o"},"product_type":"Point2D"},{"tags":["clusters","analysis"],"metadata":{},"format2d":{"title_fig":"Cluster Analysis","title_legend":null,"title_ax":"Two Clusters with Centroids","label_x":"X Position","label_y":"Y Position","lim_x_min":0.0,"lim_x_max":6.0,"lim_y_min":0.0,"lim_y_max":6.0},"x":3.4221951705447538,"y":5.3020605309178865,"marker":{"color":"red","size":50.0,"alpha":1.0,"zorder":0.0,"label":"Cluster 2","symbol":"o"},"product_type":"Point2D"},{"tags":["clusters","analysis"],"metadata":{},"format2d":{"title_fig":"Cluster Analysis","title_legend":null,"title_ax":"Two Clusters with Centroids","label_x":"X Position","label_y":"Y Position","lim_x_min":0.0,"lim_x_max":6.0,"lim_y_min":0.0,"lim_y_max":6.0},"x":3.97263195622846,"y":4.7438908278074186,"marker":{"color":"red","size":50.0,"alpha":1.0,"zorder":0.0,"label":"Cluster 2","symbol":"o"},"product_type":"Point2D"},{"tags":["clusters","analysis"],"metadata":{},"format2d":{"title_fig":"Cluster Analysis","title_legend":null,"title_ax":"Two Clusters with Centroids","label_x":"X Position","label_y":"Y Position","lim_x_min":0.0,"lim_x_max":6.0,"lim_y_min":0.0,"lim_y_max":6.0},"x":3.9146006678023455,"y":4.516825334093359,"marker":{"color":"red","size":50.0,"alpha":1.0,"zorder":0.0,"label":"Cluster 2","symbol":"o"},"product_type":"Point2D"},{"tags":["clusters","analysis"],"metadata":{},"format2d":{"title_fig":"Cluster Analysis","title_legend":null,"title_ax":"Two Clusters with Centroids","label_x":"X Position","label_y":"Y Position","lim_x_min":0.0,"lim_x_max":6.0,"lim_y_min":0.0,"lim_y_max":6.0},"x":3.864496880138455,"y":3.331679338149047,"marker":{"color":"red","size":50.0,"alpha":1.0,"zorder":0.0,"label":"Cluster 2","symbol":"o"},"product_type":"Point2D"},{"tags":["clusters","analysis"],"metadata":{},"format2d":{"title_fig":"Cluster Analysis","title_legend":null,"title_ax":"Two Clusters with Centroids","label_x":"X Position","label_y":"Y Position","lim_x_min":0.0,"lim_x_max":6.0,"lim_y_min":0.0,"lim_y_max":6.0},"x":3.2203656743825846,"y":3.753800208200412,"marker":{"color":"red","size":50.0,"alpha":1.0,"zorder":0.0,"label":"Cluster 2","symbol":"o"},"product_type":"Point2D"},{"tags":["clusters","analysis"],"metadata":{},"format2d":{"title_fig":"Cluster Analysis","title_legend":null,"title_ax":"Two Clusters with Centroids","label_x":"X Position","label_y":"Y Position","lim_x_min":0.0,"lim_x_max":6.0,"lim_y_min":0.0,"lim_y_max":6.0},"x":4.313845415058228,"y":3.4559658717169635,"marker":{"color":"red","size":50.0,"alpha":1.0,"zorder":0.0,"label":"Cluster 2","symbol":"o"},"product_type":"Point2D"},{"tags":["clusters","analysis"],"metadata":{},"format2d":{"title_fig":"Cluster Analysis","title_legend":null,"title_ax":"Two Clusters with Centroids","label_x":"X Position","label_y":"Y Position","lim_x_min":0.0,"lim_x_max":6.0,"lim_y_min":0.0,"lim_y_max":6.0},"x":4.478830603873197,"y":4.170300033463122,"marker":{"color":"red","size":50.0,"alpha":1.0,"zorder":0.0,"label":"Cluster 2","symbol":"o"},"product_type":"Point2D"},{"tags":["clusters","analysis"],"metadata":{},"format2d":{"title_fig":"Cluster Analysis","title_legend":null,"title_ax":"Two Clusters with Centroids","label_x":"X Position","label_y":"Y Position","lim_x_min":0.0,"lim_x_max":6.0,"lim_y_min":0.0,"lim_y_max":6.0},"x":4.231046748488496,"y":3.142099137971873,"marker":{"color":"red","size":50.0,"alpha":1.0,"zorder":0.0,"label":"Cluster 2","symbol":"o"},"product_type":"Point2D"},{"tags":["clusters","analysis"],"metadata":{},"format2d":{"title_fig":"Cluster Analysis","title_legend":null,"title_ax":"Two Clusters with Centroids","label_x":"X Position","label_y":"Y Position","lim_x_min":0.0,"lim_x_max":6.0,"lim_y_min":0.0,"lim_y_max":6.0},"x":4.4190749773631035,"y":3.6780223789836675,"marker":{"color":"red","size":50.0,"alpha":1.0,"zorder":0.0,"label":"Cluster 2","symbol":"o"},"product_type":"Point2D"},{"tags":["clusters","analysis"],"metadata":{},"format2d":{"title_fig":"Cluster Analysis","title_legend":null,"title_ax":"Two Clusters with Centroids","label_x":"X Position","label_y":"Y Position","lim_x_min":0.0,"lim_x_max":6.0,"lim_y_min":0.0,"lim_y_max":6.0},"x":3.3297859035607997,"y":3.4816482039366017,"marker":{"color":"red","size":50.0,"alpha":1.0,"zorder":0.0,"label":"Cluster 2","symbol":"o"},"product_type":"Point2D"},{"tags":["clusters","analysis"],"metadata":{},"format2d":{"title_fig":"Cluster Analysis","title_legend":null,"title_ax":"Two Clusters with Centroids","label_x":"X Position","label_y":"Y Position","lim_x_min":0.0,"lim_x_max":6.0,"lim_y_min":0.0,"lim_y_max":6.0},"x":4.041573451729374,"y":3.8045061392968185,"marker":{"color":"red","size":50.0,"alpha":1.0,"zorder":0.0,"label":"Cluster 2","symbol":"o"},"product_type":"Point2D"},{"tags":["clusters","analysis"],"metadata":{},"format2d":{"title_fig":"Cluster Analysis","title_legend":null,"title_ax":"Two Clusters with Centroids","label_x":"X Position","label_y":"Y Position","lim_x_min":0.0,"lim_x_max":6.0,"lim_y_min":0.0,"lim_y_max":6.0},"x":4.561754660826278,"y":3.44222064030427,"marker":{"color":"red","size":50.0,"alpha":1.0,"zorder":0.0,"label":"Cluster 2","symbol":"o"},"product_type":"Point2D"},{"tags":["clusters","analysis"],"metadata":{},"format2d":{"title_fig":"Cluster Analysis","title_legend":null,"title_ax":"Two Clusters with Centroids","label_x":"X Position","label_y":"Y Position","lim_x_min":0.0,"lim_x_max":6.0,"lim_y_min":0.0,"lim_y_max":6.0},"x":2.030439788861027,"y":2.005618234755235,"marker":{"color":"darkblue","size":200.0,"alpha":1.0,"zorder":0.0,"label":"Centroid 1","symbol":"*"},"product_type":"Point2D"},{"tags":["clusters","analysis"],"metadata":{},"format2d":{"title_fig":"Cluster Analysis","title_legend":null,"title_ax":"Two Clusters with Centroids","label_x":"X Position","label_y":"Y Position","lim_x_min":0.0,"lim_x_max":6.0,"lim_y_min":0.0,"lim_y_max":6.0},"x":3.964445487707155,"y":4.0589114035878415,"marker":{"color":"darkred","size":200.0,"alpha":1.0,"zorder":0.0,"label":"Centroid 2","symbol":"*"},"product_type":"Point2D"}]}